RiteshSum/__init__.py
RiteshSum/mysum.py
tests/__init__.py
tests/unit/__init__.py
tests/unit/test_sum.py
TanySumPkg-0.0.2.dist-info/METADATA
TanySumPkg-0.0.2.dist-info/WHEEL
TanySumPkg-0.0.2.dist-info/top_level.txt
TanySumPkg-0.0.2.dist-info/RECORD
