Metadata-Version: 2.1
Name: TanySumPkg
Version: 0.0.2
Summary: Sum Example for Packaging Practice
Author: Ritesh Patil
Author-email: <patil.ritesh311@gmail.com>
Keywords: python,video,stream,video stream,camera stream,sockets
Classifier: Development Status :: 1 - Planning
Classifier: Intended Audience :: Developers
Classifier: Programming Language :: Python :: 3
Classifier: Operating System :: Unix
Classifier: Operating System :: MacOS :: MacOS X
Classifier: Operating System :: Microsoft :: Windows
